{"trial_id": "8f9693c22539a1247b53c7426133ed9c", "hyperparameters": {"space": [{"class_name": "Int", "config": {"name": "units", "default": 101, "conditions": [], "min_value": 32, "max_value": 512, "step": 32, "sampling": null}}, {"class_name": "Float", "config": {"name": "dropout", "default": 0.0, "conditions": [], "min_value": 0.0, "max_value": 0.5, "step": 0.05, "sampling": null}}, {"class_name": "Float", "config": {"name": "learning_rate", "default": 0.0001, "conditions": [], "min_value": 1e-05, "max_value": 0.001, "step": null, "sampling": "log"}}], "values": {"units": 352, "dropout": 0.2, "learning_rate": 7.159994565305997e-05, "tuner/epochs": 2, "tuner/initial_epoch": 0, "tuner/bracket": 4, "tuner/round": 0}}, "metrics": {"metrics": {"loss": {"direction": "min", "observations": [{"value": [1.60415780544281], "step": 0}]}, "accuracy": {"direction": "max", "observations": [{"value": [0.44225189089775085], "step": 0}]}, "val_loss": {"direction": "min", "observations": [{"value": [2.0388600826263428], "step": 0}]}, "val_accuracy": {"direction": "max", "observations": [{"value": [0.11600928008556366], "step": 0}]}}}, "score": 0.11600928008556366, "best_step": 0, "status": "COMPLETED"}